stu/__init__.py
stu/bglib.py
stu/ble_wrapper.py
stu/command.py
stu/connector.py
stu/const.py
stu/graph.py
stu/part.py
stu/sensor.py
stu/upload.py
stu/data/__init__.py
stu/data/firmware.hex
pystu-0.9.8.dist-info/METADATA
pystu-0.9.8.dist-info/WHEEL
pystu-0.9.8.dist-info/entry_points.txt
pystu-0.9.8.dist-info/top_level.txt
pystu-0.9.8.dist-info/RECORD
